.editorconfig
.gitignore
.pylintrc
LICENSE.txt
README.rst
setup.py
pathmatch/__init__.py
pathmatch/fnmatch.py
pathmatch/gitmatch.py
pathmatch/helpers.py
pathmatch/pathspec.py
pathmatch/pattern.py
pathmatch/test_gitmatch.py
pathmatch/test_pathspec.py
pathmatch/test_wildmatch.py
pathmatch/wildmatch.py
pathmatch.egg-info/PKG-INFO
pathmatch.egg-info/SOURCES.txt
pathmatch.egg-info/dependency_links.txt
pathmatch.egg-info/requires.txt
pathmatch.egg-info/top_level.txt
tools/__init__.py
tools/lint.py
tools/lint_string_prefix.py