Metadata-Version: 2.1
Name: pathmatch
Version: 0.2.2
Summary: Path matching utilities
Home-page: https://github.com/demurgos/py-pathmatch
Author: Charles Samborski
Author-email: demurgos.net@gmail.com
License: MIT License
Download-URL: https://github.com/demurgos/py-pathmatch/tarball/v0.2.2
Keywords: fnmatch,wildmatch,gitignore
Platform: UNKNOWN
Classifier: Development Status :: 3 - Alpha
Classifier: Intended Audience :: Developers
Classifier: License :: OSI Approved :: MIT License
Classifier: Operating System :: OS Independent
Classifier: Programming Language :: Python :: 2.7
Classifier: Programming Language :: Python :: 3.5
Classifier: Topic :: Utilities
Provides-Extra: dev
Provides-Extra: test
